casmo4py/ColorMap.py
casmo4py/DataSelection.py
casmo4py/Legend.py
casmo4py/Map.py
casmo4py/Protocol.py
casmo4py/Setup.py
casmo4py/Utils.py
casmo4py/__init__.py
casmo4py-0.0.2.dist-info/METADATA
casmo4py-0.0.2.dist-info/WHEEL
casmo4py-0.0.2.dist-info/top_level.txt
casmo4py-0.0.2.dist-info/RECORD
