Metadata-Version: 2.4
Name: casmo4py
Version: 0.0.2
Summary: CASMO
Author-email: Tim Hake <timhake@icloud.com>
License-Expression: MIT
Project-URL: Homepage, https://www.world-stress-map.org/casmo
Classifier: Programming Language :: Python :: 3
Classifier: Operating System :: OS Independent
Requires-Python: >=3.7
